{
  "version": "1",
  "metadata": {
    "marimo_version": "0.18.1"
  },
  "cells": [
    {
      "id": "Hbol",
      "code_hash": "1d0db38904205bec4d6f6f6a1f6cec3e",
      "outputs": [
        {
          "type": "data",
          "data": {
            "text/plain": ""
          }
        }
      ],
      "console": []
    },
    {
      "id": "MJUe",
      "code_hash": "3c82725d91062ee7a62f1fd1e127e83c",
      "outputs": [
        {
          "type": "data",
          "data": {
            "text/plain": ""
          }
        }
      ],
      "console": []
    },
    {
      "id": "vblA",
      "code_hash": "b2f48ecd63ee2ecdb7e6496e8f9cbf10",
      "outputs": [
        {
          "type": "data",
          "data": {
            "text/plain": ""
          }
        }
      ],
      "console": []
    },
    {
      "id": "bkHC",
      "code_hash": "6c5659a93466d1c04093b0660e138b9a",
      "outputs": [
        {
          "type": "data",
          "data": {
            "text/plain": ""
          }
        }
      ],
      "console": []
    },
    {
      "id": "lEQa",
      "code_hash": "28b2b47d77fccdb69d6e6a4001094e7a",
      "outputs": [
        {
          "type": "data",
          "data": {
            "text/plain": ""
          }
        }
      ],
      "console": []
    },
    {
      "id": "PKri",
      "code_hash": "83cc949d144fccdd39c9e1726a06577d",
      "outputs": [
        {
          "type": "data",
          "data": {
            "text/plain": ""
          }
        }
      ],
      "console": []
    },
    {
      "id": "Xref",
      "code_hash": "49d0065ebcfc0a76d734d1a9a7ce8920",
      "outputs": [
        {
          "type": "data",
          "data": {
            "text/plain": ""
          }
        }
      ],
      "console": []
    },
    {
      "id": "SFPL",
      "code_hash": "27427ff8dc2df9c9e2fda491e447f8da",
      "outputs": [
        {
          "type": "data",
          "data": {
            "text/html": "<div style='display: flex;flex: 1;flex-direction: column;justify-content: flex-start;align-items: normal;flex-wrap: nowrap;gap: 0.5rem'><span class=\"markdown prose dark:prose-invert contents\"><h1 id=\"markdown-table-extractor-documentation\">\ud83d\udcca Markdown Table Extractor Documentation</h1></span><hr style='margin: 1rem 0; border: none; border-top: 2px solid #e0e0e0;'><marimo-ui-element object-id='SFPL-0' random-id='556596d7-55eb-0941-5bd6-0bd80a5c295c'><marimo-tabs data-initial-value='&quot;&quot;' data-label='null' data-tabs='[&quot;&lt;span class=&#92;&quot;markdown prose dark:prose-invert contents&#92;&quot;&gt;&lt;span class=&#92;&quot;paragraph&#92;&quot;&gt;&lt;iconify-icon icon=&#x27;lucide:home&#x27; inline&gt;&lt;/iconify-icon&gt; Home&lt;/span&gt;&lt;/span&gt;&quot;,&quot;&lt;span class=&#92;&quot;markdown prose dark:prose-invert contents&#92;&quot;&gt;&lt;span class=&#92;&quot;paragraph&#92;&quot;&gt;&lt;iconify-icon icon=&#x27;lucide:zap&#x27; inline&gt;&lt;/iconify-icon&gt; Quick Start&lt;/span&gt;&lt;/span&gt;&quot;,&quot;&lt;span class=&#92;&quot;markdown prose dark:prose-invert contents&#92;&quot;&gt;&lt;span class=&#92;&quot;paragraph&#92;&quot;&gt;&lt;iconify-icon icon=&#x27;lucide:package&#x27; inline&gt;&lt;/iconify-icon&gt; Modules&lt;/span&gt;&lt;/span&gt;&quot;,&quot;&lt;span class=&#92;&quot;markdown prose dark:prose-invert contents&#92;&quot;&gt;&lt;span class=&#92;&quot;paragraph&#92;&quot;&gt;&lt;iconify-icon icon=&#x27;lucide:code&#x27; inline&gt;&lt;/iconify-icon&gt; Examples&lt;/span&gt;&lt;/span&gt;&quot;,&quot;&lt;span class=&#92;&quot;markdown prose dark:prose-invert contents&#92;&quot;&gt;&lt;span class=&#92;&quot;paragraph&#92;&quot;&gt;&lt;iconify-icon icon=&#x27;lucide:book-open&#x27; inline&gt;&lt;/iconify-icon&gt; API&lt;/span&gt;&lt;/span&gt;&quot;]'><div data-kind='tab'><div style='display: flex;flex: 1;flex-direction: column;justify-content: flex-start;align-items: normal;flex-wrap: nowrap;gap: 0.5rem'><span class=\"markdown prose dark:prose-invert contents\"><h1 id=\"markdown-table-extractor\">\ud83d\udcca Markdown Table Extractor</h1>\n<blockquote>\n<span class=\"paragraph\">A Python library for extracting structured data from markdown tables,\ndesigned for processing academic manuscripts and complex documents.</span>\n</blockquote></span><marimo-callout-output data-html='&quot;&lt;span class=&#92;&quot;markdown prose dark:prose-invert contents&#92;&quot;&gt;&lt;span class=&#92;&quot;paragraph&#92;&quot;&gt;&lt;strong&gt;\u2728 Each module is an interactive marimo notebook&lt;/strong&gt; - you can run&#92;nthem as both documentation and executable code!&lt;/span&gt;&lt;/span&gt;&quot;' data-kind='&quot;success&quot;'></marimo-callout-output><span class=\"markdown prose dark:prose-invert contents\"><h2 id=\"features\">Features</h2></span><marimo-accordion data-labels='[&quot;&lt;span class=&#92;&quot;markdown prose dark:prose-invert contents&#92;&quot;&gt;&lt;span class=&#92;&quot;paragraph&#92;&quot;&gt;\ud83c\udfaf Smart Table Detection&lt;/span&gt;&lt;/span&gt;&quot;,&quot;&lt;span class=&#92;&quot;markdown prose dark:prose-invert contents&#92;&quot;&gt;&lt;span class=&#92;&quot;paragraph&#92;&quot;&gt;\ud83d\udd17 Continuation Tables&lt;/span&gt;&lt;/span&gt;&quot;,&quot;&lt;span class=&#92;&quot;markdown prose dark:prose-invert contents&#92;&quot;&gt;&lt;span class=&#92;&quot;paragraph&#92;&quot;&gt;\ud83e\uddf9 HTML Cleaning&lt;/span&gt;&lt;/span&gt;&quot;,&quot;&lt;span class=&#92;&quot;markdown prose dark:prose-invert contents&#92;&quot;&gt;&lt;span class=&#92;&quot;paragraph&#92;&quot;&gt;\ud83d\udcd1 Advanced Features&lt;/span&gt;&lt;/span&gt;&quot;]' data-multiple='true'><div><span class=\"markdown prose dark:prose-invert contents\"><ul>\n<li>Handles complex alignment syntax (<code>:--:</code>, <code>---:</code>, <code>:---</code>)</li>\n<li>Detects separator rows accurately</li>\n<li>Parses headers and data rows intelligently</li>\n</ul></span></div><div><span class=\"markdown prose dark:prose-invert contents\"><ul>\n<li>Automatically merges tables marked as \"(Continued)\"</li>\n<li>Three merge strategies available (NONE, IDENTICAL_HEADERS, COMPATIBLE_COLUMNS)</li>\n<li>Preserves captions and metadata during merging</li>\n</ul></span></div><div><span class=\"markdown prose dark:prose-invert contents\"><ul>\n<li>Removes <code>&lt;br&gt;</code> tags and other HTML artifacts</li>\n<li>Normalizes whitespace</li>\n<li>Cleans column names and cell values</li>\n</ul></span></div><div><span class=\"markdown prose dark:prose-invert contents\"><ul>\n<li><strong>Multi-level Headers</strong> - Supports sub-header rows</li>\n<li><strong>Caption Detection</strong> - Finds patterns like \"Table 3. Results\"</li>\n<li><strong>Export Formats</strong> - CSV, JSON, Excel via pandas</li>\n<li><strong>Type Hints</strong> - Full type annotations for IDE support</li>\n</ul></span></div></marimo-accordion><span class=\"markdown prose dark:prose-invert contents\"><h2 id=\"architecture\">Architecture</h2>\n<span class=\"paragraph\">The library uses a <strong>modular pipeline architecture</strong>:</span>\n<div class=\"language-text codehilite\"><pre><span></span><code>Parser \u2192 Cleaner \u2192 Merger \u2192 Extractor\n   \u2191                            \u2193\nModels \u2190\u2500\u2500\u2500\u2500\u2500\u2500\u2500\u2500\u2500\u2500\u2500\u2500\u2500\u2500\u2500\u2500\u2500\u2500\u2500\u2500\u2500\u2500\u2500\u2500\u2500\u2500\n</code></pre></div>\n<span class=\"paragraph\">Each component is independent and testable.</span></span><span class=\"markdown prose dark:prose-invert contents\"><h2 id=\"installation\">Installation</h2></span><marimo-accordion data-labels='[&quot;&lt;span class=&#92;&quot;markdown prose dark:prose-invert contents&#92;&quot;&gt;&lt;span class=&#92;&quot;paragraph&#92;&quot;&gt;pip&lt;/span&gt;&lt;/span&gt;&quot;,&quot;&lt;span class=&#92;&quot;markdown prose dark:prose-invert contents&#92;&quot;&gt;&lt;span class=&#92;&quot;paragraph&#92;&quot;&gt;uv&lt;/span&gt;&lt;/span&gt;&quot;,&quot;&lt;span class=&#92;&quot;markdown prose dark:prose-invert contents&#92;&quot;&gt;&lt;span class=&#92;&quot;paragraph&#92;&quot;&gt;poetry&lt;/span&gt;&lt;/span&gt;&quot;]' data-multiple='false'><div><span class=\"markdown prose dark:prose-invert contents\"><div class=\"language-bash codehilite\"><pre><span></span><code>pip<span class=\"w\"> </span>install<span class=\"w\"> </span>markdown-table-extractor\n</code></pre></div></span></div><div><span class=\"markdown prose dark:prose-invert contents\"><div class=\"language-bash codehilite\"><pre><span></span><code>uv<span class=\"w\"> </span>pip<span class=\"w\"> </span>install<span class=\"w\"> </span>markdown-table-extractor\n</code></pre></div></span></div><div><span class=\"markdown prose dark:prose-invert contents\"><div class=\"language-bash codehilite\"><pre><span></span><code>poetry<span class=\"w\"> </span>add<span class=\"w\"> </span>markdown-table-extractor\n</code></pre></div></span></div></marimo-accordion></div></div><div data-kind='tab'><div style='display: flex;flex: 1;flex-direction: column;justify-content: flex-start;align-items: normal;flex-wrap: nowrap;gap: 0.5rem'><span class=\"markdown prose dark:prose-invert contents\"><h1 id=\"quick-start\">\u26a1 Quick Start</h1></span><marimo-callout-output data-html='&quot;&lt;span&gt;Get started in under 5 minutes!&lt;/span&gt;&quot;' data-kind='&quot;info&quot;'></marimo-callout-output><span class=\"markdown prose dark:prose-invert contents\"><h2 id=\"installation\">Installation</h2></span><span class=\"markdown prose dark:prose-invert contents\"><div class=\"language-bash codehilite\"><pre><span></span><code>pip<span class=\"w\"> </span>install<span class=\"w\"> </span>markdown-table-extractor\n</code></pre></div></span><span class=\"markdown prose dark:prose-invert contents\"><h2 id=\"usage\">Usage</h2></span><marimo-ui-element object-id='bkHC-4' random-id='153b3c48-f571-fcb7-d966-bbb0914d2328'><marimo-tabs data-initial-value='&quot;&quot;' data-label='null' data-tabs='[&quot;&lt;span class=&#92;&quot;markdown prose dark:prose-invert contents&#92;&quot;&gt;&lt;span class=&#92;&quot;paragraph&#92;&quot;&gt;Simple API&lt;/span&gt;&lt;/span&gt;&quot;,&quot;&lt;span class=&#92;&quot;markdown prose dark:prose-invert contents&#92;&quot;&gt;&lt;span class=&#92;&quot;paragraph&#92;&quot;&gt;Full API&lt;/span&gt;&lt;/span&gt;&quot;,&quot;&lt;span class=&#92;&quot;markdown prose dark:prose-invert contents&#92;&quot;&gt;&lt;span class=&#92;&quot;paragraph&#92;&quot;&gt;Continuation Tables&lt;/span&gt;&lt;/span&gt;&quot;,&quot;&lt;span class=&#92;&quot;markdown prose dark:prose-invert contents&#92;&quot;&gt;&lt;span class=&#92;&quot;paragraph&#92;&quot;&gt;CLI&lt;/span&gt;&lt;/span&gt;&quot;]'><div data-kind='tab'><marimo-ui-element object-id='bkHC-0' random-id='c91fc348-cdee-9248-ae12-7b079d11326f'><marimo-lazy data-initial-value='false' data-label='null' data-show-loading-indicator='false'></marimo-lazy></marimo-ui-element></div><div data-kind='tab'><marimo-ui-element object-id='bkHC-1' random-id='f2950e36-d7c8-e08b-46c9-2078ec96d38d'><marimo-lazy data-initial-value='false' data-label='null' data-show-loading-indicator='false'></marimo-lazy></marimo-ui-element></div><div data-kind='tab'><marimo-ui-element object-id='bkHC-2' random-id='5295bbb0-4ad9-8b44-8673-d03df803f93f'><marimo-lazy data-initial-value='false' data-label='null' data-show-loading-indicator='false'></marimo-lazy></marimo-ui-element></div><div data-kind='tab'><marimo-ui-element object-id='bkHC-3' random-id='c7850ebb-51d4-89f5-c3ef-80186aff8509'><marimo-lazy data-initial-value='false' data-label='null' data-show-loading-indicator='false'></marimo-lazy></marimo-ui-element></div></marimo-tabs></marimo-ui-element><marimo-callout-output data-html='&quot;&lt;span class=&#92;&quot;markdown prose dark:prose-invert contents&#92;&quot;&gt;&lt;span class=&#92;&quot;paragraph&#92;&quot;&gt;&lt;strong&gt;Next:&lt;/strong&gt; Explore the Modules tab to see how each component works!&lt;/span&gt;&lt;/span&gt;&quot;' data-kind='&quot;success&quot;'></marimo-callout-output></div></div><div data-kind='tab'><div style='display: flex;flex: 1;flex-direction: column;justify-content: flex-start;align-items: normal;flex-wrap: nowrap;gap: 0.5rem'><span class=\"markdown prose dark:prose-invert contents\"><h1 id=\"module-documentation\">\ud83d\udce6 Module Documentation</h1></span><marimo-callout-output data-html='&quot;&lt;span class=&#92;&quot;markdown prose dark:prose-invert contents&#92;&quot;&gt;&lt;span class=&#92;&quot;paragraph&#92;&quot;&gt;Each module is an &lt;strong&gt;interactive marimo notebook&lt;/strong&gt;. You can:&lt;/span&gt;&#92;n&lt;ul&gt;&#92;n&lt;li&gt;\ud83d\udcd6 Read the documentation&lt;/li&gt;&#92;n&lt;li&gt;\ud83d\udd27 Modify and run the code&lt;/li&gt;&#92;n&lt;li&gt;\ud83e\uddea Experiment with live examples&lt;/li&gt;&#92;n&lt;/ul&gt;&lt;/span&gt;&quot;' data-kind='&quot;info&quot;'></marimo-callout-output><span class=\"markdown prose dark:prose-invert contents\"><h2 id=\"core-modules\">Core Modules</h2></span><marimo-accordion data-labels='[&quot;&lt;span class=&#92;&quot;markdown prose dark:prose-invert contents&#92;&quot;&gt;&lt;span class=&#92;&quot;paragraph&#92;&quot;&gt;\ud83d\udd0d Parser&lt;/span&gt;&lt;/span&gt;&quot;,&quot;&lt;span class=&#92;&quot;markdown prose dark:prose-invert contents&#92;&quot;&gt;&lt;span class=&#92;&quot;paragraph&#92;&quot;&gt;\ud83e\uddf9 Cleaner&lt;/span&gt;&lt;/span&gt;&quot;,&quot;&lt;span class=&#92;&quot;markdown prose dark:prose-invert contents&#92;&quot;&gt;&lt;span class=&#92;&quot;paragraph&#92;&quot;&gt;\ud83d\udd17 Merger&lt;/span&gt;&lt;/span&gt;&quot;,&quot;&lt;span class=&#92;&quot;markdown prose dark:prose-invert contents&#92;&quot;&gt;&lt;span class=&#92;&quot;paragraph&#92;&quot;&gt;\u2699\ufe0f Extractor&lt;/span&gt;&lt;/span&gt;&quot;,&quot;&lt;span class=&#92;&quot;markdown prose dark:prose-invert contents&#92;&quot;&gt;&lt;span class=&#92;&quot;paragraph&#92;&quot;&gt;\ud83d\udccb Models&lt;/span&gt;&lt;/span&gt;&quot;]' data-multiple='false'><div><marimo-ui-element object-id='lEQa-0' random-id='2ae3b9eb-df4e-a133-b05c-51272e3b88f8'><marimo-lazy data-initial-value='false' data-label='null' data-show-loading-indicator='false'></marimo-lazy></marimo-ui-element></div><div><marimo-ui-element object-id='lEQa-1' random-id='697857db-a6f4-ed25-8d66-5eaac9086da3'><marimo-lazy data-initial-value='false' data-label='null' data-show-loading-indicator='false'></marimo-lazy></marimo-ui-element></div><div><marimo-ui-element object-id='lEQa-2' random-id='bed4d0da-fecc-82f8-57cb-d075657ae998'><marimo-lazy data-initial-value='false' data-label='null' data-show-loading-indicator='false'></marimo-lazy></marimo-ui-element></div><div><marimo-ui-element object-id='lEQa-3' random-id='2fad2603-4c07-6b3c-4c17-dd16a67001cf'><marimo-lazy data-initial-value='false' data-label='null' data-show-loading-indicator='false'></marimo-lazy></marimo-ui-element></div><div><marimo-ui-element object-id='lEQa-4' random-id='e987e2eb-3a86-0e27-8f5a-6e2610a5e0bb'><marimo-lazy data-initial-value='false' data-label='null' data-show-loading-indicator='false'></marimo-lazy></marimo-ui-element></div></marimo-accordion><span class=\"markdown prose dark:prose-invert contents\"><h2 id=\"module-dependencies\">Module Dependencies</h2>\n<div class=\"language-ecl codehilite\"><pre><span></span><code><span class=\"nf\">graph</span><span class=\"w\"> </span><span class=\"n\">TD</span>\n<span class=\"w\">    </span><span class=\"n\">A</span><span class=\"p\">[</span><span class=\"n\">models</span><span class=\"p\">.</span><span class=\"n\">py</span><span class=\"p\">]</span><span class=\"w\"> </span><span class=\"o\">--&gt;</span><span class=\"w\"> </span><span class=\"n\">B</span><span class=\"p\">[</span><span class=\"n\">parser</span><span class=\"p\">.</span><span class=\"n\">py</span><span class=\"p\">]</span>\n<span class=\"w\">    </span><span class=\"n\">B</span><span class=\"w\"> </span><span class=\"o\">--&gt;</span><span class=\"w\"> </span><span class=\"n\">C</span><span class=\"p\">[</span><span class=\"n\">cleaner</span><span class=\"p\">.</span><span class=\"n\">py</span><span class=\"p\">]</span>\n<span class=\"w\">    </span><span class=\"n\">C</span><span class=\"w\"> </span><span class=\"o\">--&gt;</span><span class=\"w\"> </span><span class=\"n\">D</span><span class=\"p\">[</span><span class=\"n\">merger</span><span class=\"p\">.</span><span class=\"n\">py</span><span class=\"p\">]</span>\n<span class=\"w\">    </span><span class=\"n\">D</span><span class=\"w\"> </span><span class=\"o\">--&gt;</span><span class=\"w\"> </span><span class=\"n\">E</span><span class=\"p\">[</span><span class=\"n\">extractor</span><span class=\"p\">.</span><span class=\"n\">py</span><span class=\"p\">]</span>\n<span class=\"w\">    </span><span class=\"n\">A</span><span class=\"w\"> </span><span class=\"o\">--&gt;</span><span class=\"w\"> </span><span class=\"n\">E</span>\n</code></pre></div>\n<span class=\"paragraph\">Each module can be used independently or as part of the full pipeline!</span></span></div></div><div data-kind='tab'><div style='display: flex;flex: 1;flex-direction: column;justify-content: flex-start;align-items: normal;flex-wrap: nowrap;gap: 0.5rem'><span class=\"markdown prose dark:prose-invert contents\"><h1 id=\"live-examples\">\ud83d\udca1 Live Examples</h1></span><marimo-accordion data-labels='[&quot;&lt;span class=&#92;&quot;markdown prose dark:prose-invert contents&#92;&quot;&gt;&lt;span class=&#92;&quot;paragraph&#92;&quot;&gt;\ud83d\udcc4 Academic Paper Tables&lt;/span&gt;&lt;/span&gt;&quot;,&quot;&lt;span class=&#92;&quot;markdown prose dark:prose-invert contents&#92;&quot;&gt;&lt;span class=&#92;&quot;paragraph&#92;&quot;&gt;\ud83d\udcd1 Multi-page Tables&lt;/span&gt;&lt;/span&gt;&quot;,&quot;&lt;span class=&#92;&quot;markdown prose dark:prose-invert contents&#92;&quot;&gt;&lt;span class=&#92;&quot;paragraph&#92;&quot;&gt;\u2b05\ufe0f\u27a1\ufe0f Complex Alignment&lt;/span&gt;&lt;/span&gt;&quot;,&quot;&lt;span class=&#92;&quot;markdown prose dark:prose-invert contents&#92;&quot;&gt;&lt;span class=&#92;&quot;paragraph&#92;&quot;&gt;\ud83d\udcbe Export Formats&lt;/span&gt;&lt;/span&gt;&quot;,&quot;&lt;span class=&#92;&quot;markdown prose dark:prose-invert contents&#92;&quot;&gt;&lt;span class=&#92;&quot;paragraph&#92;&quot;&gt;\u2699\ufe0f Custom Merge Strategies&lt;/span&gt;&lt;/span&gt;&quot;]' data-multiple='true'><div><marimo-ui-element object-id='PKri-0' random-id='94c91bfe-4915-2c11-95a7-2f9a6be71398'><marimo-lazy data-initial-value='false' data-label='null' data-show-loading-indicator='false'></marimo-lazy></marimo-ui-element></div><div><marimo-ui-element object-id='PKri-1' random-id='289ee9bd-493c-4af0-ba0e-d112046da796'><marimo-lazy data-initial-value='false' data-label='null' data-show-loading-indicator='false'></marimo-lazy></marimo-ui-element></div><div><marimo-ui-element object-id='PKri-2' random-id='614e5f1d-4cb8-a1e4-0ec3-bea68d372f88'><marimo-lazy data-initial-value='false' data-label='null' data-show-loading-indicator='false'></marimo-lazy></marimo-ui-element></div><div><marimo-ui-element object-id='PKri-3' random-id='2b61f3e0-9516-9acb-e504-d68547d5b251'><marimo-lazy data-initial-value='false' data-label='null' data-show-loading-indicator='false'></marimo-lazy></marimo-ui-element></div><div><marimo-ui-element object-id='PKri-4' random-id='6698bc9d-1835-6901-eff2-2a3fda9a9563'><marimo-lazy data-initial-value='false' data-label='null' data-show-loading-indicator='false'></marimo-lazy></marimo-ui-element></div></marimo-accordion></div></div><div data-kind='tab'><div style='display: flex;flex: 1;flex-direction: column;justify-content: flex-start;align-items: normal;flex-wrap: nowrap;gap: 0.5rem'><span class=\"markdown prose dark:prose-invert contents\"><h1 id=\"api-reference\">\ud83d\udcd6 API Reference</h1></span><marimo-ui-element object-id='Xref-11' random-id='cb4ed278-7c62-b993-dbee-df07acb7c11f'><marimo-tabs data-initial-value='&quot;&quot;' data-label='null' data-tabs='[&quot;&lt;span class=&#92;&quot;markdown prose dark:prose-invert contents&#92;&quot;&gt;&lt;span class=&#92;&quot;paragraph&#92;&quot;&gt;Main Functions&lt;/span&gt;&lt;/span&gt;&quot;,&quot;&lt;span class=&#92;&quot;markdown prose dark:prose-invert contents&#92;&quot;&gt;&lt;span class=&#92;&quot;paragraph&#92;&quot;&gt;Data Classes&lt;/span&gt;&lt;/span&gt;&quot;,&quot;&lt;span class=&#92;&quot;markdown prose dark:prose-invert contents&#92;&quot;&gt;&lt;span class=&#92;&quot;paragraph&#92;&quot;&gt;Parser&lt;/span&gt;&lt;/span&gt;&quot;,&quot;&lt;span class=&#92;&quot;markdown prose dark:prose-invert contents&#92;&quot;&gt;&lt;span class=&#92;&quot;paragraph&#92;&quot;&gt;Cleaner&lt;/span&gt;&lt;/span&gt;&quot;,&quot;&lt;span class=&#92;&quot;markdown prose dark:prose-invert contents&#92;&quot;&gt;&lt;span class=&#92;&quot;paragraph&#92;&quot;&gt;Merger&lt;/span&gt;&lt;/span&gt;&quot;,&quot;&lt;span class=&#92;&quot;markdown prose dark:prose-invert contents&#92;&quot;&gt;&lt;span class=&#92;&quot;paragraph&#92;&quot;&gt;CLI&lt;/span&gt;&lt;/span&gt;&quot;]'><div data-kind='tab'><marimo-ui-element object-id='Xref-5' random-id='824c4681-ded2-57cd-c1d5-faafa20f5e39'><marimo-lazy data-initial-value='false' data-label='null' data-show-loading-indicator='false'></marimo-lazy></marimo-ui-element></div><div data-kind='tab'><marimo-ui-element object-id='Xref-6' random-id='8645fee6-bb56-c40f-4f95-49e210fe8df4'><marimo-lazy data-initial-value='false' data-label='null' data-show-loading-indicator='false'></marimo-lazy></marimo-ui-element></div><div data-kind='tab'><marimo-ui-element object-id='Xref-7' random-id='0bc2b300-0b88-a5d5-59d1-179856b65e2e'><marimo-lazy data-initial-value='false' data-label='null' data-show-loading-indicator='false'></marimo-lazy></marimo-ui-element></div><div data-kind='tab'><marimo-ui-element object-id='Xref-8' random-id='f975cd54-92ed-38dd-2406-5eabfb48e51f'><marimo-lazy data-initial-value='false' data-label='null' data-show-loading-indicator='false'></marimo-lazy></marimo-ui-element></div><div data-kind='tab'><marimo-ui-element object-id='Xref-9' random-id='6ecf699f-b9aa-5473-36f8-7288cf2f21d4'><marimo-lazy data-initial-value='false' data-label='null' data-show-loading-indicator='false'></marimo-lazy></marimo-ui-element></div><div data-kind='tab'><marimo-ui-element object-id='Xref-10' random-id='3f03dd6c-fab4-b005-a12a-756fee150ee4'><marimo-lazy data-initial-value='false' data-label='null' data-show-loading-indicator='false'></marimo-lazy></marimo-ui-element></div></marimo-tabs></marimo-ui-element></div></div></marimo-tabs></marimo-ui-element></div>"
          }
        }
      ],
      "console": []
    }
  ]
}